CHANGES.rst
DESCRIPTION.rst
LICENSE
MANIFEST.in
README.md
setup.py
src/wai/bynning/_Bin.py
src/wai/bynning/_BinItem.py
src/wai/bynning/_Binnable.py
src/wai/bynning/_Binning.py
src/wai/bynning/__init__.py
src/wai/bynning/_typing.py
src/wai/bynning/binners/_ArbitraryBinner.py
src/wai/bynning/binners/_Binner.py
src/wai/bynning/binners/_CrossValidationFoldBinner.py
src/wai/bynning/binners/_EqualWidthBinner.py
src/wai/bynning/binners/_FreedmanDiaconisChoiceBinning.py
src/wai/bynning/binners/_FrequencyBinner.py
src/wai/bynning/binners/_KeyBinner.py
src/wai/bynning/binners/_ManualBinner.py
src/wai/bynning/binners/_MinSizeBinner.py
src/wai/bynning/binners/_NoBinner.py
src/wai/bynning/binners/_RandomBinner.py
src/wai/bynning/binners/_RiceRuleBinner.py
src/wai/bynning/binners/_ScottsNormalReferenceRuleBinner.py
src/wai/bynning/binners/_SplitBinner.py
src/wai/bynning/binners/_SquareRootChoiceBinner.py
src/wai/bynning/binners/_StratifyingBinner.py
src/wai/bynning/binners/_SturgesFormulaBinner.py
src/wai/bynning/binners/_TwoPassBinner.py
src/wai/bynning/binners/__init__.py
src/wai/bynning/extraction/_ConstantExtractor.py
src/wai/bynning/extraction/_Extractor.py
src/wai/bynning/extraction/_IdentityExtractor.py
src/wai/bynning/extraction/_IndexExtractor.py
src/wai/bynning/extraction/_LabelExtractor.py
src/wai/bynning/extraction/_SizeExtractor.py
src/wai/bynning/extraction/__init__.py
src/wai/bynning/operations/__init__.py
src/wai/bynning/operations/_group.py
src/wai/bynning/operations/_randomised_stratified_cross_validation_folds.py
src/wai/bynning/operations/_split.py
src/wai/bynning/operations/_stratify.py
src/wai/bynning/util/__init__.py
src/wai/bynning/util/_conservatively_cache.py
src/wai/bynning/util/_frequency_divide.py
src/wai/bynning/util/_integer_dot_product.py
src/wai_bynning.egg-info/PKG-INFO
src/wai_bynning.egg-info/SOURCES.txt
src/wai_bynning.egg-info/dependency_links.txt
src/wai_bynning.egg-info/requires.txt
src/wai_bynning.egg-info/top_level.txt