Metadata-Version: 2.1
Name: wai-bynning
Version: 0.0.3
Summary: Python library for binning data, generating cross-validation fold pairs and random splits from data.
Home-page: https://github.com/waikato-datamining/bynning
Author: Corey Sterling
Author-email: coreytsterling@gmail.com
License: MIT
Classifier: Development Status :: 4 - Beta
Classifier: License :: OSI Approved :: MIT License
Classifier: Topic :: Scientific/Engineering :: Mathematics
Classifier: Programming Language :: Python :: 3
License-File: LICENSE
